capnweb/__init__.py
capnweb/py.typed
capnweb-0.1.0.dist-info/WHEEL
capnweb-0.1.0.dist-info/METADATA
capnweb-0.1.0.dist-info/RECORD
