Metadata-Version: 2.3
Name: capnweb
Version: 0.1.0
Summary: A Python implementation of the Cap'n Web RPC protocol
Author: Ramón Vila Ferreres
Author-email: Ramón Vila Ferreres <ramonvilafer@proton.me>
Requires-Python: >=3.13
